cosmos_isolation_utils/__init__.py
cosmos_isolation_utils/__main__.py
cosmos_isolation_utils/core/__init__.py
cosmos_isolation_utils/core/base_executor.py
cosmos_isolation_utils/core/config.py
cosmos_isolation_utils/core/connection.py
cosmos_isolation_utils/core/delete.py
cosmos_isolation_utils/core/dump.py
cosmos_isolation_utils/core/logging_utils.py
cosmos_isolation_utils/core/status.py
cosmos_isolation_utils/core/upload.py
cosmos_isolation_utils-0.0.4.dist-info/licenses/LICENSE
cosmos_isolation_utils-0.0.4.dist-info/METADATA
cosmos_isolation_utils-0.0.4.dist-info/WHEEL
cosmos_isolation_utils-0.0.4.dist-info/entry_points.txt
cosmos_isolation_utils-0.0.4.dist-info/top_level.txt
cosmos_isolation_utils-0.0.4.dist-info/RECORD
