Metadata-Version: 2.4
Name: cosmos-isolation-utils
Version: 0.0.4
Summary: Utilities for Azure CosmosDB isolation and testing
Author-email: Starforge Worker <star.forge.worker@gmail.com>
Maintainer-email: Starforge Worker <star.forge.worker@gmail.com>
Project-URL: Homepage, https://github.com/starforge-universe/cosmos-isolation-utils
Project-URL: Documentation, https://cosmos-isolation-utils.readthedocs.io/
Project-URL: Repository, https://github.com/starforge-universe/cosmos-isolation-utils
Project-URL: Bug Tracker, https://github.com/starforge-universe/cosmos-isolation-utils/issues
Keywords: cosmosdb,azure,database,testing,isolation,nosql
Classifier: Development Status :: 3 - Alpha
Classifier: Intended Audience :: Developers
Classifier: Operating System :: OS Independent
Classifier: Programming Language :: Python :: 3
Classifier: Programming Language :: Python :: 3.10
Classifier: Programming Language :: Python :: 3.11
Classifier: Programming Language :: Python :: 3.12
Classifier: Topic :: Software Development :: Libraries :: Python Modules
Classifier: Topic :: Database
Classifier: Topic :: Software Development :: Testing
Requires-Python: >=3.10
License-File: LICENSE
Requires-Dist: azure-cosmos>=4.0.0
Requires-Dist: click>=8.0.0
Requires-Dist: rich>=13.0.0
Requires-Dist: urllib3>=1.26.0
Provides-Extra: dev
Requires-Dist: pylint>=3.0.0; extra == "dev"
Requires-Dist: coverage>=7.0.0; extra == "dev"
Requires-Dist: sphinx>=6.0.0; extra == "dev"
Requires-Dist: sphinx-rtd-theme>=1.2.0; extra == "dev"
Dynamic: license-file
